matter_observability/__about__.py
matter_observability/__init__.py
matter_observability/config.py
matter_observability/exceptions.py
matter_observability/fastapi/__init__.py
matter_observability/fastapi/request_id.py
matter_observability/fastapi/utils.py
matter_observability/logging/__init__.py
matter_observability/logging/logging_config.py
matter_observability/metrics/__init__.py
matter_observability/metrics/custom_metrics.py
matter_observability/metrics/decorators.py
matter_observability/metrics/labeled_counter.py
matter_observability/metrics/labeled_gauge.py
matter_observability/metrics/labeled_gauge_duration.py
matter_observability/metrics/labeled_metric.py
matter_observability/metrics/utils.py
matter_observability-2.0.2.dist-info/METADATA
matter_observability-2.0.2.dist-info/WHEEL
matter_observability-2.0.2.dist-info/licenses/LICENSE
matter_observability-2.0.2.dist-info/RECORD
