Metadata-Version: 2.3
Name: matter-observability
Version: 2.0.2
Summary: A template for Matter's observability library
Project-URL: Documentation, https://github.com/Matter-Tech/matter-observability#readme
Project-URL: Issues, https://github.com/Matter-Tech/matter-observability/issues
Project-URL: Source, https://github.com/Matter-Tech/matter-observability
Author-email: Tomer Sasson <tomer@thisismatter.com>
License-Expression: MIT
License-File: LICENSE
Classifier: Development Status :: 4 - Beta
Classifier: Programming Language :: Python
Classifier: Programming Language :: Python :: 3.10
Classifier: Programming Language :: Python :: 3.11
Classifier: Programming Language :: Python :: Implementation :: CPython
Classifier: Programming Language :: Python :: Implementation :: PyPy
Requires-Python: >=3.10
Requires-Dist: fastapi>=0.90.0
Requires-Dist: matter-exceptions>=1.1.0
Requires-Dist: prometheus-fastapi-instrumentator>=6.0.0
